_telescope.cpython-36m-darwin.so
cTelescope.cpython-36m-darwin.so
parsers.cpython-36m-darwin.so
telescope/__init__.py
telescope/__main__.py
telescope/_version.py
telescope/cTelescope.cpython-36m-darwin.so
telescope/calignment.cpython-36m-darwin.so
telescope/telescope_assign.py
telescope/telescope_id.py
telescope/telescope_load.py
telescope/telescope_resume.py
telescope/telescope_tag.py
telescope/tests/__init__.py
telescope/tests/test_annotation_parsers.py
telescope/tests/test_sparse_plus.py
telescope/utils/__init__.py
telescope/utils/_alignment.py
telescope/utils/_annotation_bisect.py
telescope/utils/_annotation_htseq.py
telescope/utils/_annotation_intervaltree.py
telescope/utils/_calignment.cpython-36m-darwin.so
telescope/utils/alignment.py
telescope/utils/alignment_parsers.py
telescope/utils/annotation.py
telescope/utils/calignment.cpython-36m-darwin.so
telescope/utils/colors.py
telescope/utils/helpers.py
telescope/utils/model.py
telescope/utils/oldmodel.py
telescope/utils/sparse_plus.py
telescope_ngs-1.0.2.dist-info/LICENSE
telescope_ngs-1.0.2.dist-info/METADATA
telescope_ngs-1.0.2.dist-info/WHEEL
telescope_ngs-1.0.2.dist-info/entry_points.txt
telescope_ngs-1.0.2.dist-info/top_level.txt
telescope_ngs-1.0.2.dist-info/RECORD
