Metadata-Version: 2.1
Name: telescope-ngs
Version: 1.0.2
Summary: Single locus resolution of Transposable ELEment expression using next-generation sequencing.
Home-page: https://github.com/mlbendall/telescope
Author: Matthew L. Bendall
Author-email: bendall@gwu.edu
License: MIT
Platform: UNKNOWN
Requires-Dist: numpy (>=1.13.0)
Requires-Dist: scipy (>=0.19.0)
Requires-Dist: intervaltree
Requires-Dist: pysam (>=0.12)
Requires-Dist: HTSeq
Requires-Dist: pyyaml
Requires-Dist: future
Requires-Dist: cython
